hashi_vault/__init__.py
hashi_vault/utils.py
hashi_vault-0.1.5.dist-info/LICENSE
hashi_vault-0.1.5.dist-info/METADATA
hashi_vault-0.1.5.dist-info/WHEEL
hashi_vault-0.1.5.dist-info/top_level.txt
hashi_vault-0.1.5.dist-info/RECORD
